scripts/Commandline.py
scripts/PortalFiles.py
scripts/PortalFilesTester.py
scripts/SortSparseMatrix.py
scripts/Tester.py
scripts/__init__.py
scripts/authenticate.py
scripts/cell_ranger_to_scp.py
scripts/cli_parser.py
scripts/manage_study.py
scripts/orchestra_methods.py
scripts/scp_api.py
scripts/scp_to_infercnv.py
scripts/swap_column_values.py
scripts/verify_portal_file.py
scripts/ideogram/__init__.py
scripts/ideogram/cluster_groups.py
scripts/ideogram/matrix_to_ideogram_annots.py
single_cell_portal-0.2.2.dist-info/LICENSE.txt
single_cell_portal-0.2.2.dist-info/METADATA
single_cell_portal-0.2.2.dist-info/WHEEL
single_cell_portal-0.2.2.dist-info/entry_points.txt
single_cell_portal-0.2.2.dist-info/top_level.txt
single_cell_portal-0.2.2.dist-info/RECORD
