Metadata-Version: 2.1
Name: single-cell-portal
Version: 0.2.2
Summary: Convenience scripts for Single Cell Portal
Home-page: https://github.com/broadinstitute/single_cell_portal
Author: Single Cell Portal team
Author-email: scp-support@broadinstitute.zendesk.com
License: UNKNOWN
Platform: UNKNOWN
Classifier: Development Status :: 4 - Beta
Classifier: License :: OSI Approved :: BSD License
Classifier: Topic :: Scientific/Engineering :: Bio-Informatics
Classifier: Programming Language :: Python :: 3.7
Requires-Python: >=3.7
Requires-Dist: pandas
Requires-Dist: requests
Requires-Dist: scp-ingest-pipeline (==1.7.0)
